{
	"id": "79968d54-6675-452d-b48a-174c8f3cc0b5",
	"name": "fiapLocal",
	"values": [
		{
			"key": "AuthPort",
			"value": "5270",
			"type": "default",
			"enabled": true
		},
		{
			"key": "tokenAcesso",
			"value": "",
			"type": "default",
			"enabled": true
		},
		{
			"key": "PedidoPort",
			"value": "5271",
			"type": "default",
			"enabled": true
		},
		{
			"key": "PedidoId",
			"value": "",
			"type": "default",
			"enabled": true
		},
		{
			"key": "ProducaoPort",
			"value": "5272",
			"type": "default",
			"enabled": true
		},
		{
			"key": "PagamentoPort",
			"value": "5274",
			"type": "default",
			"enabled": true
		},
		{
			"key": "ProdutoPort",
			"value": "5273",
			"type": "default",
			"enabled": true
		},
		{
			"key": "NotificacaoPort",
			"value": "5275",
			"type": "default",
			"enabled": true
		}
	],
	"_postman_variable_scope": "environment",
	"_postman_exported_at": "2024-03-17T17:12:21.190Z",
	"_postman_exported_using": "Postman/10.24.3"
}